setup.py
hklab2/__init__.py
hklab2/cFunction.py
hklab2.egg-info/PKG-INFO
hklab2.egg-info/SOURCES.txt
hklab2.egg-info/dependency_links.txt
hklab2.egg-info/requires.txt
hklab2.egg-info/top_level.txt