Metadata-Version: 1.0
Name: hklab2
Version: 0.25
Summary: isoweek calculation and so on
Home-page: http://github.com/kimhyokwan/hklab2
Author: kimhyokwan
Author-email: haiteam@kopo.ac.kr
License: MIT
Keywords: calendar,isoweek,listsum
Platform: UNKNOWN
